simcomm/__init__.py
simcomm/core/__init__.py
simcomm/core/fading/__init__.py
simcomm/core/fading/nakagami.py
simcomm/core/fading/rayleigh.py
simcomm/core/fading/rician.py
simcomm/core/propagation/__init__.py
simcomm/core/propagation/noise.py
simcomm/core/propagation/pathloss.py
simcomm/core/simulation/__init__.py
simcomm/core/simulation/simulator.py
simcomm/core/system/__init__.py
simcomm/core/system/channel.py
simcomm/core/system/link.py
simcomm/core/system/receiver.py
simcomm/core/system/star.py
simcomm/core/system/system.py
simcomm/core/system/transmitter.py
simcomm/metrics/__init__.py
simcomm/metrics/common.py
simcomm/stats/__init__.py
simcomm/stats/common.py
simcomm/stats/metrics.py
simcomm/stats/moments.py
simcomm/utils/__init__.py
simcomm/utils/utils.py
simcomm/visualize/__init__.py
simcomm/visualize/layout.py
simcomm-0.1.4.dist-info/LICENSE
simcomm-0.1.4.dist-info/METADATA
simcomm-0.1.4.dist-info/WHEEL
simcomm-0.1.4.dist-info/top_level.txt
simcomm-0.1.4.dist-info/RECORD
