Metadata-Version: 2.1
Name: simcomm
Version: 0.1.4
Summary: SimComm is an optimized library for simulating wireless communication systems. It is purely written in Python and used NumPy and SciPy for numerical computation. It is designed to be easy to use and flexible to extend.
Home-page: https://github.com/muhd-umer/simcomm
Author: Muhammad Umer
Author-email: thisismumer@gmail.com
Project-URL: Documentation, https://simcomm.readthedocs.io
Project-URL: Bug Reports, https://github.com/muhd-umer/simcomm/issues
Project-URL: Source Code, https://github.com/muhd-umer/simcomm
Keywords: python,communication,simulator,wireless communication
Classifier: Development Status :: 5 - Production/Stable
Classifier: Intended Audience :: Developers
Classifier: Topic :: Software Development :: Build Tools
Classifier: Programming Language :: Python :: 3
Classifier: Programming Language :: Python :: 3.10
Classifier: Programming Language :: Python :: 3.11
Classifier: Programming Language :: Python :: 3 :: Only
Classifier: License :: OSI Approved :: MIT License
Classifier: Operating System :: OS Independent
Requires-Python: >=3.10
License-File: LICENSE
